Workbook

Sheet Assumptions
A1: Line | B1: 2027 | C1: 2028 | D1: 2029
A2: cost_pct | B2: 0.4 | C2: 0.4 | D2: 0.4
A3: cup_growth | B3: 0.1 | C3: 0.075 | D3: 0.05
A4: cups0 | B4: 1000 | C4: 1000 | D4: 1000
A5: price | B5: 2.5 | C5: 2.5 | D5: 2.5
A6: valuation.wacc | B6: 0.2 | C6: 0.2 | D6: 0.2
A7: valuation.terminal_growth | B7: 0 | C7: 0 | D7: 0
A8: valuation.net_cash | B8: 0 | C8: 0 | D8: 0
A9: valuation.shares | B9: 2 | C9: 2 | D9: 2

Sheet Model
A1: Line | B1: 2027 | C1: 2028 | D1: 2029
A2: cups | B2: =(Assumptions!B4*B5) -> 1100 | C2: =(Assumptions!B4*C5) -> 1182.5 | D2: =(Assumptions!B4*D5) -> 1241.625
A3: profit | B3: =(B4*(1-Assumptions!B2)) -> 1650 | C3: =(C4*(1-Assumptions!C2)) -> 1773.75 | D3: =(D4*(1-Assumptions!D2)) -> 1862.4375
A4: revenue | B4: =(B2*Assumptions!B5) -> 2750 | C4: =(C2*Assumptions!C5) -> 2956.25 | D4: =(D2*Assumptions!D5) -> 3104.0625
A5: _grow_factor_1 | B5: =(1*(1+Assumptions!B3)) -> 1.1 | C5: =(B5*(1+Assumptions!C3)) -> 1.1825 | D5: =(C5*(1+Assumptions!D3)) -> 1.241625

Sheet DCF
A1: Line | B1: 2027 | C1: 2028 | D1: 2029
A2: FCF | B2: =Model!B3 -> 1650 | C2: =Model!C3 -> 1773.75 | D2: =Model!D3 -> 1862.4375
A3: WACC | B3: =Assumptions!B6 -> 0.2 | C3: =Assumptions!C6 -> 0.2 | D3: =Assumptions!D6 -> 0.2
A4: Discount factor | B4: =1*(1+B3) -> 1.2 | C4: =B4*(1+C3) -> 1.44 | D4: =C4*(1+D3) -> 1.728
A5: Present value | B5: =B2/B4 -> 1375 | C5: =C2/C4 -> 1231.7708 | D5: =D2/D4 -> 1077.7995
A7: Terminal value | B7: =D2*(1+Assumptions!D7)/(D3-Assumptions!D7) -> 9312.1875
A8: Terminal present value | B8: =B7/D4 -> 5388.9974
A9: Enterprise value | B9: =SUM(B5:D5)+B8 -> 9073.5677
A10: Net cash | B10: =Assumptions!B8 -> 0
A11: Equity value | B11: =B9+B10 -> 9073.5677
A12: Shares | B12: =Assumptions!B9 -> 2
A13: Per-share value | B13: =B11/B12 -> 4536.7839
A14: Terminal weight | B14: =B8/B9 -> 0.59392265

Sheet Actuals
A1: period | B1: line | C1: value
A2: 2025 | B2: cups | C2: 900
A3: 2025 | B3: revenue | C3: 2160
A4: 2026 | B4: cups | C4: 1000
A5: 2026 | B5: revenue | C5: 2500
