Workbook

Sheet Assumptions
A1: Line | B1: 1 | C1: 2 | D1: 3 | E1: 4 | F1: 5 | G1: 6
A2: beta | B2: 0.8 | C2: 0.8 | D2: 0.8 | E2: 0.8 | F2: 0.8 | G2: 0.8
A3: capex0 | B3: 2152 | C3: 2152 | D3: 2152 | E3: 2152 | F3: 2152 | G3: 2152
A4: cash | B4: 500 | C4: 500 | D4: 500 | E4: 500 | F4: 500 | G4: 500
A5: debt | B5: 1822 | C5: 1822 | D5: 1822 | E5: 1822 | F5: 1822 | G5: 1822
A6: debt_cost | B6: 0.055 | C6: 0.055 | D6: 0.055 | E6: 0.055 | F6: 0.055 | G6: 0.055
A7: depreciation0 | B7: 1228 | C7: 1228 | D7: 1228 | E7: 1228 | F7: 1228 | G7: 1228
A8: ebit0 | B8: 5186 | C8: 5186 | D8: 5186 | E8: 5186 | F8: 5186 | G8: 5186
A9: high_phase | B9: 1 | C9: 1 | D9: 1 | E9: 1 | F9: 1 | G9: 0
A10: high_years | B10: 5 | C10: 5 | D10: 5 | E10: 5 | F10: 5 | G10: 5
A11: options | B11: 1500 | C11: 1500 | D11: 1500 | E11: 1500 | F11: 1500 | G11: 1500
A12: prior_book_debt | B12: 1315 | C12: 1315 | D12: 1315 | E12: 1315 | F12: 1315 | G12: 1315
... A27: valuation.shares | B27: 993.57 | C27: 993.57 | D27: 993.57 | E27: 993.57 | F27: 993.57 | G27: 993.57

Sheet Model
A1: Line | B1: 1 | C1: 2 | D1: 3 | E1: 4 | F1: 5 | G1: 6
A2: after_tax_debt_cost | B2: =(Assumptions!B6*(1-Assumptions!B21)) -> 0.0393305 | C2: =(Assumptions!C6*(1-Assumptions!C21)) -> 0.0393305 | D2: =(Assumptions!D6*(1-Assumptions!D21)) -> 0.0393305 | E2: =(Assumptions!E6*(1-Assumptions!E21)) -> 0.0393305 | F2: =(Assumptions!F6*(1-Assumptions!F21)) -> 0.0393305 | G2: =(Assumptions!G6*(1-Assumptions!G21)) -> 0.0393305
A3: capex_high | B3: =(Assumptions!B3*B30) -> 2379.3251 | C3: =(Assumptions!B3*C30) -> 2630.6635 | D3: =(Assumptions!B3*D30) -> 2908.5518 | E3: =(Assumptions!B3*E30) -> 3215.7947 | F3: =(Assumptions!B3*F30) -> 3555.493 | G3: =(Assumptions!B3*G30) -> 3931.0752
A4: cost_of_equity | B4: =(Assumptions!B16+(Assumptions!B2*Assumptions!B15)) -> 0.097 | C4: =(Assumptions!C16+(Assumptions!C2*Assumptions!C15)) -> 0.097 | D4: =(Assumptions!D16+(Assumptions!D2*Assumptions!D15)) -> 0.097 | E4: =(Assumptions!E16+(Assumptions!E2*Assumptions!E15)) -> 0.097 | F4: =(Assumptions!F16+(Assumptions!F2*Assumptions!F15)) -> 0.097 | G4: =(Assumptions!G16+(Assumptions!G2*Assumptions!G15)) -> 0.097
A5: cumulative_pv_fcff | B5: =((0*Assumptions!B4)+B21) -> 2446.6941 | C5: =(B5+C21) -> 4914.5141 | D5: =(C5+D21) -> 7403.6425 | E5: =(D5+E21) -> 9914.2632 | F5: =(E5+F21) -> 12446.562 | G5: =(F5+G21) -> 14318.392
A6: debt_weight | B6: =(1-B12) -> 0.01440145 | C6: =(1-C12) -> 0.01440145 | D6: =(1-D12) -> 0.01440145 | E6: =(1-E12) -> 0.01440145 | F6: =(1-F12) -> 0.01440145 | G6: =(1-G12) -> 0.01440145
A7: depreciation_high | B7: =(Assumptions!B7*B31) -> 1357.719 | C7: =(Assumptions!B7*C31) -> 1501.1407 | D7: =(Assumptions!B7*D31) -> 1659.7127 | E7: =(Assumptions!B7*E31) -> 1835.0353 | F7: =(Assumptions!B7*F31) -> 2028.878 | G7: =(Assumptions!B7*G31) -> 2243.1972
A8: discount_factor | B8: =(1*B32) -> 1.0961695 | C8: =(1*C32) -> 1.2015875 | D8: =(1*D32) -> 1.3171436 | E8: =(1*E32) -> 1.4438126 | F8: =(1*F32) -> 1.5826633 | G8: =(1*G32) -> 1.7348672
A9: enterprise_value | B9: =(B5+B22) -> 57257.572 | C9: =(C5+C22) -> 60198.655 | D9: =(D5+D22) -> 63165.133 | E9: =(E5+E22) -> 66157.225 | F9: =(F5+F22) -> 69175.152 | G9: =(G5+G22) -> 69175.152
A10: equity_after_options | B10: =(B11-Assumptions!B11) -> 54435.572 | C10: =(C11-Assumptions!C11) -> 57376.655 | D10: =(D11-Assumptions!D11) -> 60343.133 | E10: =(E11-Assumptions!E11) -> 63335.225 | F10: =(F11-Assumptions!F11) -> 66353.152 | G10: =(G11-Assumptions!G11) -> 66353.152
A11: equity_before_options | B11: =((B9+Assumptions!B4)-Assumptions!B5) -> 55935.572 | C11: =((C9+Assumptions!C4)-Assumptions!C5) -> 58876.655 | D11: =((D9+Assumptions!D4)-Assumptions!D5) -> 61843.133 | E11: =((E9+Assumptions!E4)-Assumptions!E5) -> 64835.225 | F11: =((F9+Assumptions!F4)-Assumptions!F5) -> 67853.152 | G11: =((G9+Assumptions!G4)-Assumptions!G5) -> 67853.152
A12: equity_weight | B12: =((Assumptions!B17*Assumptions!B18)/(Assumptions!B5+(Assumptions!B17*Assumptions!B18))) -> 0.98559855 | C12: =((Assumptions!C17*Assumptions!C18)/(Assumptions!C5+(Assumptions!C17*Assumptions!C18))) -> 0.98559855 | D12: =((Assumptions!D17*Assumptions!D18)/(Assumptions!D5+(Assumptions!D17*Assumptions!D18))) -> 0.98559855 | E12: =((Assumptions!E17*Assumptions!E18)/(Assumptions!E5+(Assumptions!E17*Assumptions!E18))) -> 0.98559855 | F12: =((Assumptions!F17*Assumptions!F18)/(Assumptions!F5+(Assumptions!F17*Assumptions!F18))) -> 0.98559855 | G12: =((Assumptions!G17*Assumptions!G18)/(Assumptions!G5+(Assumptions!G17*Assumptions!G18))) -> 0.98559855
A13: fcff | B13: =((B19-B17)-B28) -> 2681.9914 | C13: =((C19-C17)-C28) -> 2965.3017 | D13: =((D19-D17)-D28) -> 3278.5394 | E13: =((E19-E17)-E28) -> 3624.8657 | F13: =((F19-F17)-F28) -> 4007.7759 | G13: =((G19-G17)-G28) -> 3247.3771
A14: growth | B14: =((Assumptions!B9*B15)+((1-Assumptions!B9)*Assumptions!B19)) -> 0.10563433 | C14: =((Assumptions!C9*C15)+((1-Assumptions!C9)*Assumptions!C19)) -> 0.10563433 | D14: =((Assumptions!D9*D15)+((1-Assumptions!D9)*Assumptions!D19)) -> 0.10563433 | E14: =((Assumptions!E9*E15)+((1-Assumptions!E9)*Assumptions!E19)) -> 0.10563433 | F14: =((Assumptions!F9*F15)+((1-Assumptions!F9)*Assumptions!F19)) -> 0.10563433 | G14: =((Assumptions!G9*G15)+((1-Assumptions!G9)*Assumptions!G19)) -> 0.06
A15: high_growth | B15: =(B24*B23) -> 0.10563433 | C15: =(C24*C23) -> 0.10563433 | D15: =(D24*D23) -> 0.10563433 | E15: =(E24*E23) -> 0.10563433 | F15: =(F24*F23) -> 0.10563433 | G15: =(G24*G23) -> 0.10563433
A16: horizon | B16: =Assumptions!B10 -> 5 | C16: =Assumptions!C10 -> 5 | D16: =Assumptions!D10 -> 5 | E16: =Assumptions!E10 -> 5 | F16: =Assumptions!F10 -> 5 | G16: =Assumptions!G10 -> 5
A17: net_capex | B17: =((Assumptions!B9*(B3-B7))+((1-Assumptions!B9)*(((Assumptions!B19/Assumptions!B20)*B19)-B28))) -> 1021.6061 | C17: =((Assumptions!C9*(C3-C7))+((1-Assumptions!C9)*(((Assumptions!C19/Assumptions!C20)*C19)-C28))) -> 1129.5228 | D17: =((Assumptions!D9*(D3-D7))+((1-Assumptions!D9)*(((Assumptions!D19/Assumptions!D20)*D19)-D28))) -> 1248.8392 | E17: =((Assumptions!E9*(E3-E7))+((1-Assumptions!E9)*(((Assumptions!E19/Assumptions!E20)*E19)-E28))) -> 1380.7595 | F17: =((Assumptions!F9*(F3-F7))+((1-Assumptions!F9)*(((Assumptions!F19/Assumptions!F20)*F19)-F28))) -> 1526.615 | G17: =((Assumptions!G9*(G3-G7))+((1-Assumptions!G9)*(((Assumptions!G19/Assumptions!G20)*G19)-G28))) -> 2875.1408
A18: net_cash_after_options | B18: =((Assumptions!B4-Assumptions!B5)-Assumptions!B11) -> -2822 | C18: =((Assumptions!C4-Assumptions!C5)-Assumptions!C11) -> -2822 | D18: =((Assumptions!D4-Assumptions!D5)-Assumptions!D11) -> -2822 | E18: =((Assumptions!E4-Assumptions!E5)-Assumptions!E11) -> -2822 | F18: =((Assumptions!F4-Assumptions!F5)-Assumptions!F11) -> -2822 | G18: =((Assumptions!G4-Assumptions!G5)-Assumptions!G11) -> -2822
A19: nopat | B19: =((Assumptions!B8*(1-Assumptions!B21))*B33) -> 4100.2544 | C19: =((Assumptions!B8*(1-Assumptions!B21))*C33) -> 4533.382 | D19: =((Assumptions!B8*(1-Assumptions!B21))*D33) -> 5012.2628 | E19: =((Assumptions!B8*(1-Assumptions!B21))*E33) -> 5541.7298 | F19: =((Assumptions!B8*(1-Assumptions!B21))*F33) -> 6127.1266 | G19: =((Assumptions!B8*(1-Assumptions!B21))*G33) -> 6494.7542
A20: per_share | B20: =(B10/Assumptions!B18) -> 54.787858 | C20: =(C10/Assumptions!C18) -> 57.747975 | D20: =(D10/Assumptions!D18) -> 60.733651 | E20: =(E10/Assumptions!E18) -> 63.745106 | F20: =(F10/Assumptions!F18) -> 66.782564 | G20: =(G10/Assumptions!G18) -> 66.782564
A21: pv_fcff | B21: =(B13/B8) -> 2446.6941 | C21: =(C13/C8) -> 2467.82 | D21: =(D13/D8) -> 2489.1284 | E21: =(E13/E8) -> 2510.6207 | F21: =(F13/F8) -> 2532.2986 | G21: =(G13/G8) -> 1871.8304
A22: pv_terminal | B22: =(B26/B8) -> 54810.878 | C22: =(C26/C8) -> 55284.141 | D22: =(D26/D8) -> 55761.491 | E22: =(E26/E8) -> 56242.962 | F22: =(F26/F8) -> 56728.591 | G22: =(G26/G8) -> 54856.76
A23: reinvestment_rate | B23: =(((Assumptions!B3-Assumptions!B7)+Assumptions!B23)/(Assumptions!B8*(1-Assumptions!B21))) -> 0.3837122 | C23: =(((Assumptions!C3-Assumptions!C7)+Assumptions!C23)/(Assumptions!C8*(1-Assumptions!C21))) -> 0.3837122 | D23: =(((Assumptions!D3-Assumptions!D7)+Assumptions!D23)/(Assumptions!D8*(1-Assumptions!D21))) -> 0.3837122 | E23: =(((Assumptions!E3-Assumptions!E7)+Assumptions!E23)/(Assumptions!E8*(1-Assumptions!E21))) -> 0.3837122 | F23: =(((Assumptions!F3-Assumptions!F7)+Assumptions!F23)/(Assumptions!F8*(1-Assumptions!F21))) -> 0.3837122 | G23: =(((Assumptions!G3-Assumptions!G7)+Assumptions!G23)/(Assumptions!G8*(1-Assumptions!G21))) -> 0.3837122
A24: return_on_capital | B24: =((Assumptions!B8*(1-Assumptions!B21))/(Assumptions!B12+Assumptions!B13)) -> 0.27529572 | C24: =((Assumptions!C8*(1-Assumptions!C21))/(Assumptions!C12+Assumptions!C13)) -> 0.27529572 | D24: =((Assumptions!D8*(1-Assumptions!D21))/(Assumptions!D12+Assumptions!D13)) -> 0.27529572 | E24: =((Assumptions!E8*(1-Assumptions!E21))/(Assumptions!E12+Assumptions!E13)) -> 0.27529572 | F24: =((Assumptions!F8*(1-Assumptions!F21))/(Assumptions!F12+Assumptions!F13)) -> 0.27529572 | G24: =((Assumptions!G8*(1-Assumptions!G21))/(Assumptions!G12+Assumptions!G13)) -> 0.27529572
A25: revenue | B25: =(Assumptions!B14*B34) -> 18465.199 | C25: =(Assumptions!B14*C34) -> 20415.758 | D25: =(Assumptions!B14*D34) -> 22572.362 | E25: =(Assumptions!B14*E34) -> 24956.779 | F25: =(Assumptions!B14*F34) -> 27593.071 | G25: =(Assumptions!B14*G34) -> 29248.656
A26: terminal_value | B26: =(((B19*(1+Assumptions!B19))*(1-(Assumptions!B19/Assumptions!B20)))/(B27-Assumptions!B19)) -> 60082.011 | C26: =(((C19*(1+Assumptions!C19))*(1-(Assumptions!C19/Assumptions!C20)))/(C27-Assumptions!C19)) -> 66428.734 | D26: =(((D19*(1+Assumptions!D19))*(1-(Assumptions!D19/Assumptions!D20)))/(D27-Assumptions!D19)) -> 73445.888 | E26: =(((E19*(1+Assumptions!E19))*(1-(Assumptions!E19/Assumptions!E20)))/(E27-Assumptions!E19)) -> 81204.295 | F26: =(((F19*(1+Assumptions!F19))*(1-(Assumptions!F19/Assumptions!F20)))/(F27-Assumptions!F19)) -> 89782.256 | G26: =(((G19*(1+Assumptions!G19))*(1-(Assumptions!G19/Assumptions!G20)))/(G27-Assumptions!G19)) -> 95169.192
A27: wacc | B27: =((B4*B12)+(B2*B6)) -> 0.096169476 | C27: =((C4*C12)+(C2*C6)) -> 0.096169476 | D27: =((D4*D12)+(D2*D6)) -> 0.096169476 | E27: =((E4*E12)+(E2*E6)) -> 0.096169476 | F27: =((F4*F12)+(F2*F6)) -> 0.096169476 | G27: =((G4*G12)+(G2*G6)) -> 0.096169476
A28: working_capital_change | B28: =((B25-Assumptions!B14)*B29) -> 396.65689 | C28: =((C25-B25)*C29) -> 438.55748 | D28: =((D25-C25)*D29) -> 484.8842 | E28: =((E25-D25)*E29) -> 536.10461 | F28: =((F25-E25)*F29) -> 592.73566 | G28: =((G25-F25)*G29) -> 372.23633
A29: working_capital_ratio | B29: =MAX((Assumptions!B22/Assumptions!B14),0) -> 0.22483684 | C29: =MAX((Assumptions!C22/Assumptions!C14),0) -> 0.22483684 | D29: =MAX((Assumptions!D22/Assumptions!D14),0) -> 0.22483684 | E29: =MAX((Assumptions!E22/Assumptions!E14),0) -> 0.22483684 | F29: =MAX((Assumptions!F22/Assumptions!F14),0) -> 0.22483684 | G29: =MAX((Assumptions!G22/Assumptions!G14),0) -> 0.22483684
A30: _grow_factor_1 | B30: =(1*(1+B15)) -> 1.1056343 | C30: =(B30*(1+C15)) -> 1.2224273 | D30: =(C30*(1+D15)) -> 1.3515575 | E30: =(D30*(1+E15)) -> 1.4943284 | F30: =(E30*(1+F15)) -> 1.6521808 | G30: =(F30*(1+G15)) -> 1.8267078
A31: _grow_factor_2 | B31: =(1*(1+B15)) -> 1.1056343 | C31: =(B31*(1+C15)) -> 1.2224273 | D31: =(C31*(1+D15)) -> 1.3515575 | E31: =(D31*(1+E15)) -> 1.4943284 | F31: =(E31*(1+F15)) -> 1.6521808 | G31: =(F31*(1+G15)) -> 1.8267078
A32: _grow_factor_3 | B32: =(1*(1+B27)) -> 1.0961695 | C32: =(B32*(1+C27)) -> 1.2015875 | D32: =(C32*(1+D27)) -> 1.3171436 | E32: =(D32*(1+E27)) -> 1.4438126 | F32: =(E32*(1+F27)) -> 1.5826633 | G32: =(F32*(1+G27)) -> 1.7348672
A33: _grow_factor_4 | B33: =(1*(1+B14)) -> 1.1056343 | C33: =(B33*(1+C14)) -> 1.2224273 | D33: =(C33*(1+D14)) -> 1.3515575 | E33: =(D33*(1+E14)) -> 1.4943284 | F33: =(E33*(1+F14)) -> 1.6521808 | G33: =(F33*(1+G14)) -> 1.7513116
A34: _grow_factor_5 | B34: =(1*(1+B14)) -> 1.1056343 | C34: =(B34*(1+C14)) -> 1.2224273 | D34: =(C34*(1+D14)) -> 1.3515575 | E34: =(D34*(1+E14)) -> 1.4943284 | F34: =(E34*(1+F14)) -> 1.6521808 | G34: =(F34*(1+G14)) -> 1.7513116

Sheet DCF
A1: Line | B1: 1 | C1: 2 | D1: 3 | E1: 4 | F1: 5 | G1: 6
A2: FCF | B2: =Model!B13 -> 2681.9914 | C2: =Model!C13 -> 2965.3017 | D2: =Model!D13 -> 3278.5394 | E2: =Model!E13 -> 3624.8657 | F2: =Model!F13 -> 4007.7759 | G2: =Model!G13 -> 3247.3771
A3: WACC | B3: =Assumptions!B24 -> 0.096169476 | C3: =Assumptions!C24 -> 0.096169476 | D3: =Assumptions!D24 -> 0.096169476 | E3: =Assumptions!E24 -> 0.096169476 | F3: =Assumptions!F24 -> 0.096169476 | G3: =Assumptions!G24 -> 0.096169476
A4: Discount factor | B4: =1*(1+B3) -> 1.0961695 | C4: =B4*(1+C3) -> 1.2015875 | D4: =C4*(1+D3) -> 1.3171436 | E4: =D4*(1+E3) -> 1.4438126 | F4: =E4*(1+F3) -> 1.5826633 | G4: =F4*(1+G3) -> 1.7348672
A5: Present value | B5: =B2/B4 -> 2446.6941 | C5: =C2/C4 -> 2467.82 | D5: =D2/D4 -> 2489.1284 | E5: =E2/E4 -> 2510.6207 | F5: =F2/F4 -> 2532.2986 | G5: =G2/G4 -> 1871.8304
A7: Terminal value | B7: =G2*(1+Assumptions!G25)/(G3-Assumptions!G25) -> 95169.192
A8: Terminal present value | B8: =B7/G4 -> 54856.76
A9: Enterprise value | B9: =SUM(B5:G5)+B8 -> 69175.152
A10: Net cash | B10: =Assumptions!B26 -> -2822
A11: Equity value | B11: =B9+B10 -> 66353.152
A12: Shares | B12: =Assumptions!B27 -> 993.57
A13: Per-share value | B13: =B11/B12 -> 66.782564
A14: Terminal weight | B14: =B8/B9 -> 0.79301249

Sheet Actuals
A1: period | B1: line | C1: value
