Workbook

Sheet Inputs
A1: Input | B1: Value | D1: Fixed source selections
A2: beta | B2: 0.8 | D2: Public equity market weights; unchanged debt ratio in stable period
A3: capex0 | B3: 2152 | D3: CAPM cost of equity; beta and debt cost unchanged in stable period
A4: cash | B4: 500 | D4: Fundamental growth, using current reinvestment rate and prior book capital
A5: debt | B5: 1822 | D5: Capex, depreciation and revenue grow with earnings
A6: debt_cost | B6: 0.055 | D6: Current working capital / revenue ratio, floored at zero
A7: depreciation0 | B7: 1228 | D7: Stable reinvestment = stable growth / stable return on capital
A8: ebit0 | B8: 5186 | D8: Five explicit forecast years, followed by terminal year
A9: high_years | B9: 5
A10: options | B10: 1500
A11: prior_book_debt | B11: 1315
A12: prior_book_equity | B12: 12156
A13: revenue0 | B13: 16701
A14: risk_premium | B14: 0.055
A15: riskfree | B15: 0.053
A16: share_price | B16: 125.5
A17: shares | B17: 993.57
A18: stable_growth | B18: 0.06
A19: stable_roc | B19: 0.12
A20: tax_rate | B20: 0.2849
... A22: working_capital_change0 | B22: 499

Sheet Model
A1: Derived assumption | B1: Live formula
A2: Current NOPAT | B2: =Inputs!$B$8*(1-Inputs!$B$20)
A3: Return on capital | B3: =B2/(Inputs!$B$11+Inputs!$B$12)
A4: Reinvestment rate | B4: =(Inputs!$B$3-Inputs!$B$7+Inputs!$B$22)/B2
A5: High growth | B5: =B3*B4
A6: Cost of equity | B6: =Inputs!$B$15+Inputs!$B$2*Inputs!$B$14
A7: Equity weight | B7: =Inputs!$B$16*Inputs!$B$17/(Inputs!$B$5+Inputs!$B$16*Inputs!$B$17)
A8: Debt weight | B8: =1-B7
A9: After-tax debt cost | B9: =Inputs!$B$6*(1-Inputs!$B$20)
A10: WACC (both stages) | B10: =B6*B7+B9*B8
A11: Working capital ratio | B11: =MAX(0,Inputs!$B$21/Inputs!$B$13)
A12: Stable growth | B12: =Inputs!$B$18
A13: Stable return on capital | B13: =Inputs!$B$19
A15: Forecast metric | B15: 1 | C15: 2 | D15: 3 | E15: 4 | F15: 5 | G15: Terminal year
A16: NOPAT | B16: =$B$2*(1+$B$5) | C16: =B16*(1+$B$5) | D16: =C16*(1+$B$5) | E16: =D16*(1+$B$5) | F16: =E16*(1+$B$5) | G16: =$B$2*(1+$B$5)^Inputs!$B$9*(1+$B$12)
A17: Net capital spending | B17: =Inputs!$B$3*(1+$B$5)^B$15-Inputs!$B$7*(1+$B$5)^B$15 | C17: =Inputs!$B$3*(1+$B$5)^C$15-Inputs!$B$7*(1+$B$5)^C$15 | D17: =Inputs!$B$3*(1+$B$5)^D$15-Inputs!$B$7*(1+$B$5)^D$15 | E17: =Inputs!$B$3*(1+$B$5)^E$15-Inputs!$B$7*(1+$B$5)^E$15 | F17: =Inputs!$B$3*(1+$B$5)^F$15-Inputs!$B$7*(1+$B$5)^F$15 | G17: =($B$12/$B$13)*G16-G18
A18: Change in working capital | B18: =Inputs!$B$13*$B$11*((1+$B$5)^B$15-(1+$B$5)^(B$15-1)) | C18: =Inputs!$B$13*$B$11*((1+$B$5)^C$15-(1+$B$5)^(C$15-1)) | D18: =Inputs!$B$13*$B$11*((1+$B$5)^D$15-(1+$B$5)^(D$15-1)) | E18: =Inputs!$B$13*$B$11*((1+$B$5)^E$15-(1+$B$5)^(E$15-1)) | F18: =Inputs!$B$13*$B$11*((1+$B$5)^F$15-(1+$B$5)^(F$15-1)) | G18: =(Inputs!$B$13*(1+$B$5)^Inputs!$B$9*(1+$B$12)-Inputs!$B$13*(1+$B$5)^Inputs!$B$9)*$B$11
A19: FCFF | B19: =B16-B17-B18 | C19: =C16-C17-C18 | D19: =D16-D17-D18 | E19: =E16-E17-E18 | F19: =F16-F17-F18 | G19: =G16-G17-G18
A20: Present value of FCFF | B20: =B19/(1+$B$10)^B$15 | C20: =C19/(1+$B$10)^C$15 | D20: =D19/(1+$B$10)^D$15 | E20: =E19/(1+$B$10)^E$15 | F20: =F19/(1+$B$10)^F$15
A23: Terminal value | B23: =G19/(B10-B12)
A24: PV terminal value | B24: =B23/(1+B10)^Inputs!$B$9
A25: PV explicit cash flows | B25: =SUM(B20:F20)
A26: Enterprise value | B26: =B24+B25
A27: Equity before options | B27: =B26+Inputs!$B$4-Inputs!$B$5
A28: Equity per share | B28: =(B27-Inputs!$B$10)/Inputs!$B$17

Sheet Outputs
A1: Contract metric | B1: Value 1 | C1: Value 2 | D1: Value 3 | E1: Value 4 | F1: Value 5 | G1: Terminal / value 6
A2: after_tax_debt_cost | B2: =Model!B9
A3: cost_of_equity | B3: =Model!B6
A4: debt_weight | B4: =Model!B8
A5: equity_before_options | B5: =Model!B27
A6: ev | B6: =Model!B26
A7: fcff | B7: =Model!B19 | C7: =Model!C19 | D7: =Model!D19 | E7: =Model!E19 | F7: =Model!F19 | G7: =Model!G19
A8: high_growth | B8: =Model!B5
A9: net_capex | B9: =Model!B17 | C9: =Model!C17 | D9: =Model!D17 | E9: =Model!E17 | F9: =Model!F17 | G9: =Model!G17
A10: nopat | B10: =Model!B16 | C10: =Model!C16 | D10: =Model!D16 | E10: =Model!E16 | F10: =Model!F16 | G10: =Model!G16
A11: per_share | B11: =Model!B28
A12: pv_fcff | B12: =Model!B20 | C12: =Model!C20 | D12: =Model!D20 | E12: =Model!E20 | F12: =Model!F20
A13: pv_terminal | B13: =Model!B24
A14: terminal_value | B14: =Model!B23
A15: wacc | B15: =Model!B10
A16: working_capital_change | B16: =Model!B18 | C16: =Model!C18 | D16: =Model!D18 | E16: =Model!E18 | F16: =Model!F18 | G16: =Model!G18
A17: working_capital_ratio | B17: =Model!B11
