Workbook

Sheet Assumptions
A1: Line | B1: 2026 | C1: 2027 | D1: 2028 | E1: 2029 | F1: 2030
A2: capex_pct | B2: 0.065 | C2: 0.06375 | D2: 0.0625 | E2: 0.06125 | F2: 0.06
A3: company_revenue0 | B3: 30744.8 | C3: 30744.8 | D3: 30744.8 | E3: 30744.8 | F3: 30744.8
A4: da_pct | B4: 0.047 | C4: 0.047 | D4: 0.047 | E4: 0.047 | F4: 0.047
A5: footprint_growth | B5: 0.02 | C5: 0.02 | D5: 0.02 | E5: 0.02 | F5: 0.02
A6: incremental_nwc_pct | B6: 0.02 | C6: 0.02 | D6: 0.02 | E6: 0.02 | F6: 0.02
A7: licensed_growth | B7: 0.04 | C7: 0.04 | D7: 0.04 | E7: 0.04 | F7: 0.04
A8: licensed_revenue0 | B8: 4350.4 | C8: 4350.4 | D8: 4350.4 | E8: 4350.4 | F8: 4350.4
A9: operating_margin | B9: 0.1 | C9: 0.11 | D9: 0.12 | E9: 0.13 | F9: 0.14
A10: other_growth | B10: 0.04 | C10: 0.04 | D10: 0.04 | E10: 0.04 | F10: 0.04
A11: other_revenue0 | B11: 2089.2 | C11: 2089.2 | D11: 2089.2 | E11: 2089.2 | F11: 2089.2
A12: revenue0 | B12: 37184.4 | C12: 37184.4 | D12: 37184.4 | E12: 37184.4 | F12: 37184.4
... A19: valuation.shares | B19: 1136.9 | C19: 1136.9 | D19: 1136.9 | E19: 1136.9 | F19: 1136.9

Sheet Model
A1: Line | B1: 2026 | C1: 2027 | D1: 2028 | E1: 2029 | F1: 2030
A2: capex | B2: =(B12*Assumptions!B2) -> 2535.2563 | C2: =(C12*Assumptions!C2) -> 2618.9267 | D2: =(D12*Assumptions!D2) -> 2715.4991 | E2: =(E12*Assumptions!E2) -> 2826.2012 | F2: =(F12*Assumptions!F2) -> 2952.4944
A3: cash_taxes | B3: =(MAX(B7,0)*Assumptions!B13) -> 975.09857 | C3: =(MAX(C7,0)*Assumptions!C13) -> 1129.7331 | D3: =(MAX(D7,0)*Assumptions!D13) -> 1303.4396 | E3: =(MAX(E7,0)*Assumptions!E13) -> 1499.617 | F3: =(MAX(F7,0)*Assumptions!F13) -> 1722.2884
A4: company_growth | B4: =((((1+Assumptions!B5)*(1+Assumptions!B15))*(1+Assumptions!B14))-1) -> 0.050804 | C4: =((((1+Assumptions!C5)*(1+Assumptions!C15))*(1+Assumptions!C14))-1) -> 0.056006 | D4: =((((1+Assumptions!D5)*(1+Assumptions!D15))*(1+Assumptions!D14))-1) -> 0.061208 | E4: =((((1+Assumptions!E5)*(1+Assumptions!E15))*(1+Assumptions!E14))-1) -> 0.06641 | F4: =((((1+Assumptions!F5)*(1+Assumptions!F15))*(1+Assumptions!F14))-1) -> 0.071612
A5: company_revenue | B5: =(Assumptions!B3*B13) -> 32306.759 | C5: =(Assumptions!B3*C13) -> 34116.131 | D5: =(Assumptions!B3*D13) -> 36204.311 | E5: =(Assumptions!B3*E13) -> 38608.64 | F5: =(Assumptions!B3*F13) -> 41373.482
A6: da | B6: =(B12*Assumptions!B4) -> 1833.1853 | C6: =(C12*Assumptions!C4) -> 1930.8165 | D6: =(D12*Assumptions!D4) -> 2042.0553 | E6: =(E12*Assumptions!E4) -> 2168.6769 | F6: =(F12*Assumptions!F4) -> 2312.7873
A7: ebit | B7: =(B12*Assumptions!B9) -> 3900.3943 | C7: =(C12*Assumptions!C9) -> 4518.9323 | D7: =(D12*Assumptions!D9) -> 5213.7583 | E7: =(E12*Assumptions!E9) -> 5998.4679 | F7: =(F12*Assumptions!F9) -> 6889.1535
A8: fcff | B8: =((((B7-B3)+B6)-B2)-B9) -> 2186.8339 | C8: =((((C7-C3)+C6)-C2)-C9) -> 2659.5439 | D8: =((((D7-D3)+D6)-D2)-D9) -> 3189.5393 | E8: =((((E7-E3)+E6)-E2)-E9) -> 3787.4451 | F8: =((((F7-F3)+F6)-F2)-F9) -> 4465.8345
A9: incremental_nwc | B9: =((B12-Assumptions!B12)*Assumptions!B6) -> 36.390856 | C9: =((C12-B12)*Assumptions!C6) -> 41.545194 | D9: =((D12-C12)*Assumptions!D6) -> 47.33566 | E9: =((E12-D12)*Assumptions!E6) -> 53.881506 | F9: =((F12-E12)*Assumptions!F6) -> 61.323575
A10: licensed_revenue | B10: =(Assumptions!B8*B14) -> 4524.416 | C10: =(Assumptions!B8*C14) -> 4705.3926 | D10: =(Assumptions!B8*D14) -> 4893.6083 | E10: =(Assumptions!B8*E14) -> 5089.3527 | F10: =(Assumptions!B8*F14) -> 5292.9268
A11: other_revenue | B11: =(Assumptions!B11*B15) -> 2172.768 | C11: =(Assumptions!B11*C15) -> 2259.6787 | D11: =(Assumptions!B11*D15) -> 2350.0659 | E11: =(Assumptions!B11*E15) -> 2444.0685 | F11: =(Assumptions!B11*F15) -> 2541.8312
A12: revenue | B12: =((B5+B10)+B11) -> 39003.943 | C12: =((C5+C10)+C11) -> 41081.203 | D12: =((D5+D10)+D11) -> 43447.986 | E12: =((E5+E10)+E11) -> 46142.061 | F12: =((F5+F10)+F11) -> 49208.24
A13: _grow_factor_1 | B13: =(1*(1+B4)) -> 1.050804 | C13: =(B13*(1+C4)) -> 1.1096553 | D13: =(C13*(1+D4)) -> 1.1775751 | E13: =(D13*(1+E4)) -> 1.2557779 | F13: =(E13*(1+F4)) -> 1.3457066
A14: _grow_factor_2 | B14: =(1*(1+Assumptions!B7)) -> 1.04 | C14: =(B14*(1+Assumptions!C7)) -> 1.0816 | D14: =(C14*(1+Assumptions!D7)) -> 1.124864 | E14: =(D14*(1+Assumptions!E7)) -> 1.1698586 | F14: =(E14*(1+Assumptions!F7)) -> 1.2166529
A15: _grow_factor_3 | B15: =(1*(1+Assumptions!B10)) -> 1.04 | C15: =(B15*(1+Assumptions!C10)) -> 1.0816 | D15: =(C15*(1+Assumptions!D10)) -> 1.124864 | E15: =(D15*(1+Assumptions!E10)) -> 1.1698586 | F15: =(E15*(1+Assumptions!F10)) -> 1.2166529

Sheet DCF
A1: Line | B1: 2026 | C1: 2027 | D1: 2028 | E1: 2029 | F1: 2030
A2: FCF | B2: =Model!B8 -> 2186.8339 | C2: =Model!C8 -> 2659.5439 | D2: =Model!D8 -> 3189.5393 | E2: =Model!E8 -> 3787.4451 | F2: =Model!F8 -> 4465.8345
A3: WACC | B3: =Assumptions!B16 -> 0.09 | C3: =Assumptions!C16 -> 0.09 | D3: =Assumptions!D16 -> 0.09 | E3: =Assumptions!E16 -> 0.09 | F3: =Assumptions!F16 -> 0.09
A4: Discount factor | B4: =1*(1+B3) -> 1.09 | C4: =B4*(1+C3) -> 1.1881 | D4: =C4*(1+D3) -> 1.295029 | E4: =D4*(1+E3) -> 1.4115816 | F4: =E4*(1+F3) -> 1.538624
A5: Present value | B5: =B2/B4 -> 2006.2696 | C5: =C2/C4 -> 2238.4849 | D5: =D2/D4 -> 2462.9095 | E5: =E2/E4 -> 2683.1216 | F5: =F2/F4 -> 2902.486
A7: Terminal value | B7: =F2*(1+Assumptions!F17)/(F3-Assumptions!F17) -> 70422.774
A8: Terminal present value | B8: =B7/F4 -> 45769.971
A9: Enterprise value | B9: =SUM(B5:F5)+B8 -> 58063.243
A10: Net cash | B10: =Assumptions!B18 -> -12615.2
A11: Equity value | B11: =B9+B10 -> 45448.043
A12: Shares | B12: =Assumptions!B19 -> 1136.9
A13: Per-share value | B13: =B11/B12 -> 39.975409
A14: Terminal weight | B14: =B8/B9 -> 0.7882779

Sheet Actuals
A1: period | B1: line | C1: value
A2: 2024 | B2: capex | C2: 2777.5
A3: 2024 | B3: company_revenue | C3: 29765.9
A4: 2024 | B4: da | C4: 1592.4
A5: 2024 | B5: ebit | C5: 5408.8
A6: 2024 | B6: licensed_revenue | C6: 4505.1
A7: 2024 | B7: operating_cash_flow | C7: 6095.6
A8: 2024 | B8: other_revenue | C8: 1905.2
A9: 2024 | B9: revenue | C9: 36176.2
A10: 2025 | B10: capex | C10: 2305.5
A11: 2025 | B11: company_revenue | C11: 30744.8
A12: 2025 | B12: da | C12: 1771.5
A13: 2025 | B13: ebit | C13: 2936.6
... A17: 2025 | B17: revenue | C17: 37184.4
