Workbook

Sheet Assumptions
A1: Line | B1: 1
A2: beta | B2: 1.1
A3: capex_depreciation_ratio | B3: 1.25
A4: debt_cost | B4: 0.085
A5: debt_weight | B5: 0.2997
A6: depreciation0 | B6: 400
A7: ebit0 | B7: 1535
A8: risk_premium | B8: 0.055
A9: riskfree | B9: 0.07
A10: stable_growth | B10: 0.05
A11: tax_rate | B11: 0.36
A12: working_capital_change0 | B12: 160
A13: valuation.wacc | B13: =Model!B8 -> 0.10769283
A14: valuation.terminal_growth | B14: =Assumptions!B10 -> 0.05
A15: valuation.net_cash | B15: 0
A16: valuation.shares | B16: 1

Sheet Model
A1: Line | B1: 1
A2: after_tax_debt_cost | B2: =(Assumptions!B4*(1-Assumptions!B11)) -> 0.0544
A3: cost_of_equity | B3: =(Assumptions!B9+(Assumptions!B2*Assumptions!B8)) -> 0.1305
A4: fcff | B4: =(B5*(1*B10)) -> 758.52
A5: fcff_current | B5: =((B7-B6)-B9) -> 722.4
A6: net_capex_current | B6: =((Assumptions!B3-1)*Assumptions!B6) -> 100
A7: nopat_current | B7: =(Assumptions!B7*(1-Assumptions!B11)) -> 982.4
A8: wacc | B8: =((B3*(1-Assumptions!B5))+(B2*Assumptions!B5)) -> 0.10769283
A9: working_capital_change_current | B9: =Assumptions!B12 -> 160
A10: _grow_factor_1 | B10: =(1*(1+Assumptions!B10)) -> 1.05

Sheet DCF
A1: Line | B1: 1
A2: FCF | B2: =Model!B4 -> 758.52
A3: WACC | B3: =Assumptions!B13 -> 0.10769283
A4: Discount factor | B4: =1*(1+B3) -> 1.1076928
A5: Present value | B5: =B2/B4 -> 684.77468
A7: Terminal value | B7: =B2*(1+Assumptions!B14)/(B3-Assumptions!B14) -> 13804.939
A8: Terminal present value | B8: =B7/B4 -> 12462.786
A9: Enterprise value | B9: =SUM(B5:B5)+B8 -> 13147.561
A10: Net cash | B10: =Assumptions!B15 -> 0
A11: Equity value | B11: =B9+B10 -> 13147.561
A12: Shares | B12: =Assumptions!B16 -> 1
A13: Per-share value | B13: =B11/B12 -> 13147.561
A14: Terminal weight | B14: =B8/B9 -> 0.94791622

Sheet Actuals
A1: period | B1: line | C1: value
