Workbook

Sheet Assumptions
A1: Line | B1: 1 | C1: 2 | D1: 3 | E1: 4 | F1: 5 | G1: 6
A2: beta | B2: 0.8 | C2: 0.8 | D2: 0.8 | E2: 0.8 | F2: 0.8 | G2: 0.8
A3: capex0 | B3: 2152 | C3: 2152 | D3: 2152 | E3: 2152 | F3: 2152 | G3: 2152
A4: debt_cost | B4: 0.055 | C4: 0.055 | D4: 0.055 | E4: 0.055 | F4: 0.055 | G4: 0.055
A5: debt_weight | B5: 0.01440145 | C5: 0.01440145 | D5: 0.01440145 | E5: 0.01440145 | F5: 0.01440145 | G5: 0.01440145
A6: depreciation0 | B6: 1228 | C6: 1228 | D6: 1228 | E6: 1228 | F6: 1228 | G6: 1228
A7: ebit0 | B7: 5186 | C7: 5186 | D7: 5186 | E7: 5186 | F7: 5186 | G7: 5186
A8: growth_profile | B8: 0.10563433 | C8: 0.10563433 | D8: 0.10563433 | E8: 0.10563433 | F8: 0.10563433 | G8: 0.06
A9: high_growth | B9: 0.10563433 | C9: 0.10563433 | D9: 0.10563433 | E9: 0.10563433 | F9: 0.10563433 | G9: 0.10563433
A10: revenue0 | B10: 16701 | C10: 16701 | D10: 16701 | E10: 16701 | F10: 16701 | G10: 16701
A11: risk_premium | B11: 0.055 | C11: 0.055 | D11: 0.055 | E11: 0.055 | F11: 0.055 | G11: 0.055
A12: riskfree | B12: 0.053 | C12: 0.053 | D12: 0.053 | E12: 0.053 | F12: 0.053 | G12: 0.053
... A17: working_capital0 | B17: 3755 | C17: 3755 | D17: 3755 | E17: 3755 | F17: 3755 | G17: 3755
A18: valuation.wacc | B18: =Model!B15 -> 0.096169476 | C18: =Model!C15 -> 0.096169476 | D18: =Model!D15 -> 0.096169476 | E18: =Model!E15 -> 0.096169476 | F18: =Model!F15 -> 0.096169476 | G18: =Model!G15 -> 0.096169476
A19: valuation.terminal_growth | B19: =Assumptions!B13 -> 0.06 | C19: =Assumptions!C13 -> 0.06 | D19: =Assumptions!D13 -> 0.06 | E19: =Assumptions!E13 -> 0.06 | F19: =Assumptions!F13 -> 0.06 | G19: =Assumptions!G13 -> 0.06
A20: valuation.net_cash | B20: -2822 | C20: -2822 | D20: -2822 | E20: -2822 | F20: -2822 | G20: -2822
A21: valuation.shares | B21: 993.57 | C21: 993.57 | D21: 993.57 | E21: 993.57 | F21: 993.57 | G21: 993.57

Sheet Model
A1: Line | B1: 1 | C1: 2 | D1: 3 | E1: 4 | F1: 5 | G1: 6
A2: after_tax_debt_cost | B2: =(Assumptions!B4*(1-Assumptions!B16)) -> 0.0393305 | C2: =(Assumptions!C4*(1-Assumptions!C16)) -> 0.0393305 | D2: =(Assumptions!D4*(1-Assumptions!D16)) -> 0.0393305 | E2: =(Assumptions!E4*(1-Assumptions!E16)) -> 0.0393305 | F2: =(Assumptions!F4*(1-Assumptions!F16)) -> 0.0393305 | G2: =(Assumptions!G4*(1-Assumptions!G16)) -> 0.0393305
A3: cost_of_equity | B3: =(Assumptions!B12+(Assumptions!B2*Assumptions!B11)) -> 0.097 | C3: =(Assumptions!C12+(Assumptions!C2*Assumptions!C11)) -> 0.097 | D3: =(Assumptions!D12+(Assumptions!D2*Assumptions!D11)) -> 0.097 | E3: =(Assumptions!E12+(Assumptions!E2*Assumptions!E11)) -> 0.097 | F3: =(Assumptions!F12+(Assumptions!F2*Assumptions!F11)) -> 0.097 | G3: =(Assumptions!G12+(Assumptions!G2*Assumptions!G11)) -> 0.097
A4: debt_ratio | B4: =Assumptions!B5 -> 0.01440145 | C4: =Assumptions!C5 -> 0.01440145 | D4: =Assumptions!D5 -> 0.01440145 | E4: =Assumptions!E5 -> 0.01440145 | F4: =Assumptions!F5 -> 0.01440145 | G4: =Assumptions!G5 -> 0.01440145
A5: depreciation | B5: =(Assumptions!B6*B18) -> 1357.719 | C5: =(Assumptions!B6*C18) -> 1501.1407 | D5: =(Assumptions!B6*D18) -> 1659.7127 | E5: =(Assumptions!B6*E18) -> 1835.0353 | F5: =(Assumptions!B6*F18) -> 2028.878 | G5: =(Assumptions!B6*G18) -> 2150.6107
A6: discount_factor | B6: =(1*B19) -> 1.0961695 | C6: =(1*C19) -> 1.2015875 | D6: =(1*D19) -> 1.3171436 | E6: =(1*E19) -> 1.4438126 | F6: =(1*F19) -> 1.5826633 | G6: =(1*G19) -> 1.7348672
A7: ebit | B7: =(Assumptions!B7*B20) -> 5733.8196 | C7: =(Assumptions!B7*C20) -> 6339.5078 | D7: =(Assumptions!B7*D20) -> 7009.1774 | E7: =(Assumptions!B7*E20) -> 7749.5871 | F7: =(Assumptions!B7*F20) -> 8568.2095 | G7: =(Assumptions!B7*G20) -> 9082.3021
A8: fcff | B8: =((B12-B11)-B16) -> 2681.9914 | C8: =((C12-C11)-C16) -> 2965.3017 | D8: =((D12-D11)-D16) -> 3278.5394 | E8: =((E12-E11)-E16) -> 3624.8657 | F8: =((F12-F11)-F16) -> 4007.7759 | G8: =((G12-G11)-G16) -> 3247.3771
A9: growth_assumption | B9: =Assumptions!B9 -> 0.10563433 | C9: =Assumptions!C9 -> 0.10563433 | D9: =Assumptions!D9 -> 0.10563433 | E9: =Assumptions!E9 -> 0.10563433 | F9: =Assumptions!F9 -> 0.10563433 | G9: =Assumptions!G9 -> 0.10563433
A10: high_capex | B10: =(Assumptions!B3*B21) -> 2379.3251 | C10: =(Assumptions!B3*C21) -> 2630.6635 | D10: =(Assumptions!B3*D21) -> 2908.5518 | E10: =(Assumptions!B3*E21) -> 3215.7947 | F10: =(Assumptions!B3*F21) -> 3555.493 | G10: =(Assumptions!B3*G21) -> 3768.8226
A11: net_capex | B11: =(((1-Assumptions!B15)*(B10-B5))+(Assumptions!B15*(((B12*Assumptions!B13)/Assumptions!B14)-B16))) -> 1021.6061 | C11: =(((1-Assumptions!C15)*(C10-C5))+(Assumptions!C15*(((C12*Assumptions!C13)/Assumptions!C14)-C16))) -> 1129.5228 | D11: =(((1-Assumptions!D15)*(D10-D5))+(Assumptions!D15*(((D12*Assumptions!D13)/Assumptions!D14)-D16))) -> 1248.8392 | E11: =(((1-Assumptions!E15)*(E10-E5))+(Assumptions!E15*(((E12*Assumptions!E13)/Assumptions!E14)-E16))) -> 1380.7595 | F11: =(((1-Assumptions!F15)*(F10-F5))+(Assumptions!F15*(((F12*Assumptions!F13)/Assumptions!F14)-F16))) -> 1526.615 | G11: =(((1-Assumptions!G15)*(G10-G5))+(Assumptions!G15*(((G12*Assumptions!G13)/Assumptions!G14)-G16))) -> 2875.1408
A12: nopat | B12: =(B7*(1-Assumptions!B16)) -> 4100.2544 | C12: =(C7*(1-Assumptions!C16)) -> 4533.382 | D12: =(D7*(1-Assumptions!D16)) -> 5012.2628 | E12: =(E7*(1-Assumptions!E16)) -> 5541.7298 | F12: =(F7*(1-Assumptions!F16)) -> 6127.1266 | G12: =(G7*(1-Assumptions!G16)) -> 6494.7542
A13: pv_fcff | B13: =(B8/B6) -> 2446.6941 | C13: =(C8/C6) -> 2467.82 | D13: =(D8/D6) -> 2489.1284 | E13: =(E8/E6) -> 2510.6207 | F13: =(F8/F6) -> 2532.2986 | G13: =(G8/G6) -> 1871.8304
A14: revenue | B14: =(Assumptions!B10*B22) -> 18465.199 | C14: =(Assumptions!B10*C22) -> 20415.758 | D14: =(Assumptions!B10*D22) -> 22572.362 | E14: =(Assumptions!B10*E22) -> 24956.779 | F14: =(Assumptions!B10*F22) -> 27593.071 | G14: =(Assumptions!B10*G22) -> 29248.656
A15: wacc | B15: =((B3*(1-Assumptions!B5))+(B2*Assumptions!B5)) -> 0.096169476 | C15: =((C3*(1-Assumptions!C5))+(C2*Assumptions!C5)) -> 0.096169476 | D15: =((D3*(1-Assumptions!D5))+(D2*Assumptions!D5)) -> 0.096169476 | E15: =((E3*(1-Assumptions!E5))+(E2*Assumptions!E5)) -> 0.096169476 | F15: =((F3*(1-Assumptions!F5))+(F2*Assumptions!F5)) -> 0.096169476 | G15: =((G3*(1-Assumptions!G5))+(G2*Assumptions!G5)) -> 0.096169476
A16: working_capital_change | B16: =((B14-Assumptions!B10)*B17) -> 396.65689 | C16: =((C14-B14)*C17) -> 438.55748 | D16: =((D14-C14)*D17) -> 484.8842 | E16: =((E14-D14)*E17) -> 536.10461 | F16: =((F14-E14)*F17) -> 592.73566 | G16: =((G14-F14)*G17) -> 372.23633
A17: working_capital_ratio | B17: =MAX((Assumptions!B17/Assumptions!B10),0) -> 0.22483684 | C17: =MAX((Assumptions!C17/Assumptions!C10),0) -> 0.22483684 | D17: =MAX((Assumptions!D17/Assumptions!D10),0) -> 0.22483684 | E17: =MAX((Assumptions!E17/Assumptions!E10),0) -> 0.22483684 | F17: =MAX((Assumptions!F17/Assumptions!F10),0) -> 0.22483684 | G17: =MAX((Assumptions!G17/Assumptions!G10),0) -> 0.22483684
A18: _grow_factor_1 | B18: =(1*(1+Assumptions!B8)) -> 1.1056343 | C18: =(B18*(1+Assumptions!C8)) -> 1.2224273 | D18: =(C18*(1+Assumptions!D8)) -> 1.3515575 | E18: =(D18*(1+Assumptions!E8)) -> 1.4943284 | F18: =(E18*(1+Assumptions!F8)) -> 1.6521808 | G18: =(F18*(1+Assumptions!G8)) -> 1.7513116
A19: _grow_factor_2 | B19: =(1*(1+B15)) -> 1.0961695 | C19: =(B19*(1+C15)) -> 1.2015875 | D19: =(C19*(1+D15)) -> 1.3171436 | E19: =(D19*(1+E15)) -> 1.4438126 | F19: =(E19*(1+F15)) -> 1.5826633 | G19: =(F19*(1+G15)) -> 1.7348672
A20: _grow_factor_3 | B20: =(1*(1+Assumptions!B8)) -> 1.1056343 | C20: =(B20*(1+Assumptions!C8)) -> 1.2224273 | D20: =(C20*(1+Assumptions!D8)) -> 1.3515575 | E20: =(D20*(1+Assumptions!E8)) -> 1.4943284 | F20: =(E20*(1+Assumptions!F8)) -> 1.6521808 | G20: =(F20*(1+Assumptions!G8)) -> 1.7513116
A21: _grow_factor_4 | B21: =(1*(1+Assumptions!B8)) -> 1.1056343 | C21: =(B21*(1+Assumptions!C8)) -> 1.2224273 | D21: =(C21*(1+Assumptions!D8)) -> 1.3515575 | E21: =(D21*(1+Assumptions!E8)) -> 1.4943284 | F21: =(E21*(1+Assumptions!F8)) -> 1.6521808 | G21: =(F21*(1+Assumptions!G8)) -> 1.7513116
A22: _grow_factor_5 | B22: =(1*(1+Assumptions!B8)) -> 1.1056343 | C22: =(B22*(1+Assumptions!C8)) -> 1.2224273 | D22: =(C22*(1+Assumptions!D8)) -> 1.3515575 | E22: =(D22*(1+Assumptions!E8)) -> 1.4943284 | F22: =(E22*(1+Assumptions!F8)) -> 1.6521808 | G22: =(F22*(1+Assumptions!G8)) -> 1.7513116

Sheet DCF
A1: Line | B1: 1 | C1: 2 | D1: 3 | E1: 4 | F1: 5 | G1: 6
A2: FCF | B2: =Model!B8 -> 2681.9914 | C2: =Model!C8 -> 2965.3017 | D2: =Model!D8 -> 3278.5394 | E2: =Model!E8 -> 3624.8657 | F2: =Model!F8 -> 4007.7759 | G2: =Model!G8 -> 3247.3771
A3: WACC | B3: =Assumptions!B18 -> 0.096169476 | C3: =Assumptions!C18 -> 0.096169476 | D3: =Assumptions!D18 -> 0.096169476 | E3: =Assumptions!E18 -> 0.096169476 | F3: =Assumptions!F18 -> 0.096169476 | G3: =Assumptions!G18 -> 0.096169476
A4: Discount factor | B4: =1*(1+B3) -> 1.0961695 | C4: =B4*(1+C3) -> 1.2015875 | D4: =C4*(1+D3) -> 1.3171436 | E4: =D4*(1+E3) -> 1.4438126 | F4: =E4*(1+F3) -> 1.5826633 | G4: =F4*(1+G3) -> 1.7348672
A5: Present value | B5: =B2/B4 -> 2446.6941 | C5: =C2/C4 -> 2467.82 | D5: =D2/D4 -> 2489.1284 | E5: =E2/E4 -> 2510.6207 | F5: =F2/F4 -> 2532.2986 | G5: =G2/G4 -> 1871.8304
A7: Terminal value | B7: =G2*(1+Assumptions!G19)/(G3-Assumptions!G19) -> 95169.192
A8: Terminal present value | B8: =B7/G4 -> 54856.76
A9: Enterprise value | B9: =SUM(B5:G5)+B8 -> 69175.152
A10: Net cash | B10: =Assumptions!B20 -> -2822
A11: Equity value | B11: =B9+B10 -> 66353.152
A12: Shares | B12: =Assumptions!B21 -> 993.57
A13: Per-share value | B13: =B11/B12 -> 66.782564
A14: Terminal weight | B14: =B8/B9 -> 0.79301249

Sheet Actuals
A1: period | B1: line | C1: value
